odoo/addons/l10n_it_financial_statement_eu/README.rst
odoo/addons/l10n_it_financial_statement_eu/__init__.py
odoo/addons/l10n_it_financial_statement_eu/__manifest__.py
odoo/addons/l10n_it_financial_statement_eu/hooks.py
odoo/addons/l10n_it_financial_statement_eu/data/financial.statement.eu.csv
odoo/addons/l10n_it_financial_statement_eu/i18n/it.po
odoo/addons/l10n_it_financial_statement_eu/i18n/l10n_it_financial_statement_eu.pot
odoo/addons/l10n_it_financial_statement_eu/migrations/16.0.1.0.0/pre-migrate.py
odoo/addons/l10n_it_financial_statement_eu/models/__init__.py
odoo/addons/l10n_it_financial_statement_eu/models/financial_statement_eu.py
odoo/addons/l10n_it_financial_statement_eu/readme/CONFIGURE.md
odoo/addons/l10n_it_financial_statement_eu/readme/CONTRIBUTORS.md
odoo/addons/l10n_it_financial_statement_eu/readme/DESCRIPTION.md
odoo/addons/l10n_it_financial_statement_eu/readme/USAGE.md
odoo/addons/l10n_it_financial_statement_eu/report/__init__.py
odoo/addons/l10n_it_financial_statement_eu/report/financial_statement_eu_report.py
odoo/addons/l10n_it_financial_statement_eu/report/financial_statement_eu_report.xml
odoo/addons/l10n_it_financial_statement_eu/report/templates/layouts.xml
odoo/addons/l10n_it_financial_statement_eu/security/financial_statement_eu_security.xml
odoo/addons/l10n_it_financial_statement_eu/static/description/icon.png
odoo/addons/l10n_it_financial_statement_eu/static/description/index.html
odoo/addons/l10n_it_financial_statement_eu/static/src/css/report.css
odoo/addons/l10n_it_financial_statement_eu/static/src/js/client_action.esm.js
odoo/addons/l10n_it_financial_statement_eu/static/src/xml/report.xml
odoo/addons/l10n_it_financial_statement_eu/tests/__init__.py
odoo/addons/l10n_it_financial_statement_eu/tests/test_financial_statement_eu.py
odoo/addons/l10n_it_financial_statement_eu/views/financial_statement_eu_view.xml
odoo/addons/l10n_it_financial_statement_eu/wizard/__init__.py
odoo_addon_l10n_it_financial_statement_eu-18.0.1.0.0.3.dist-info/METADATA
odoo_addon_l10n_it_financial_statement_eu-18.0.1.0.0.3.dist-info/WHEEL
odoo_addon_l10n_it_financial_statement_eu-18.0.1.0.0.3.dist-info/top_level.txt
odoo_addon_l10n_it_financial_statement_eu-18.0.1.0.0.3.dist-info/RECORD
