Metadata-Version: 2.1
Name: odoo-addon-l10n_it_financial_statement_eu
Version: 18.0.1.0.0.3
Requires-Python: >=3.10
Requires-Dist: odoo-addon-date_range==18.0.*
Requires-Dist: odoo-addon-report_xlsx==18.0.*
Requires-Dist: odoo-addon-report_xml==18.0.*
Requires-Dist: odoo==18.0.*
Summary: ITA - Bilancio UE con XBRL
Home-page: https://github.com/OCA/l10n-italy
License: AGPL-3
Author: MKT Srl, Odoo Community Association (OCA)
Author-email: support@odoo-community.org
Classifier: Programming Language :: Python
Classifier: Framework :: Odoo
Classifier: Framework :: Odoo :: 18.0
Classifier: License :: OSI Approved :: GNU Affero General Public License v3
Classifier: Development Status :: 4 - Beta
